[
  {
    "title": "Sign a petition telling Mayor London Breed to Raise Wages for Economic Recovery. ",
    "link": "https://actionnetwork.org/petitions/raise-wages-for-economic-recovery?source=email&;"
  },

  {
    "name": "Divestment Campaign",
    "content": "https://www.livingwage-sf.org/mass-incarceration/divesting-from-mass-incarceration/"
  },

  {
    "title": "Sign a petition telling Mayor London Breed to Raise Wages for Economic Recovery. ",
    "link": "https://actionnetwork.org/petitions/raise-wages-for-economic-recovery?source=email&;"
  },

  {
    "title": "Sign a petition telling Mayor London Breed to Raise Wages for Economic Recovery. ",
    "link": "https://actionnetwork.org/petitions/raise-wages-for-economic-recovery?source=email&;"
  },

  {
    "title": "Support Maquiladora Workers in Ciudad Juarez",
    "link": "https://www.paypal.com/donate?token=Z3jBesiTEjrBGxbhz3pRTWS9da-hghiVhcqkkqFb8d4VSigwX_ji_eGazKdGTWQ3gXJTfZ1qG9kXmevW"
  }
]
